LICENSE
MANIFEST.in
README.rst
setup.py
fixDict.egg-info/PKG-INFO
fixDict.egg-info/SOURCES.txt
fixDict.egg-info/dependency_links.txt
fixDict.egg-info/top_level.txt
fixDict.egg-info/zip-safe
fixdict/__init__.py
fixdict/fix_dict.py